{"name":"Gravity","tagline":"Gravity, a gravity simulator.","body":"# Gravity\r\n## What's it do\r\nSimulates a particle field and is currently beig worked on to create random systems.\r\n## Authors and Contributors\r\n[Taken from Ian Mallet's work on Gravitation](http://geometrian.com/programming/projects/index.php?project=Gravitation)\r\n\r\nThis fork of Gravitation is called Gravity and is worked on and maintained by:\r\n- @Toggle2\r\n- @KnightHawk3","google":"","note":"Don't delete this file! It's used internally to help with page regeneration."}